MANIFEST.in
README.txt
setup.py
docs/HISTORY.txt
src/dolmen/__init__.py
src/dolmen.forms.base.egg-info/PKG-INFO
src/dolmen.forms.base.egg-info/SOURCES.txt
src/dolmen.forms.base.egg-info/dependency_links.txt
src/dolmen.forms.base.egg-info/namespace_packages.txt
src/dolmen.forms.base.egg-info/not-zip-safe
src/dolmen.forms.base.egg-info/requires.txt
src/dolmen.forms.base.egg-info/top_level.txt
src/dolmen/forms/__init__.py
src/dolmen/forms/base/README.txt
src/dolmen/forms/base/__init__.py
src/dolmen/forms/base/interfaces.py
src/dolmen/forms/base/tests.py