Metadata-Version: 1.0
Name: dolmen.forms.base
Version: 0.1
Summary: Forms meta-package for Dolmen, using megrok.z3cform.base and z3c.form
Home-page: UNKNOWN
Author: Souheil Chelfouh
Author-email: trollfot@gmail.com
License: GPL
Keywords: Dolmen Forms
Platform: UNKNOWN
Classifier: Development Status :: 4 - Beta
Classifier: Environment :: Web Environment
Classifier: Framework :: Zope3
Classifier: Intended Audience :: Other Audience
Classifier: License :: OSI Approved :: GNU General Public License (GPL)
Classifier: Operating System :: OS Independent
Classifier: Programming Language :: Python
